{
  "timestamp": 1755618856480,
  "uptimeSec": 1826,
  "startTime": 1755617030395,
  "spawned": {
    "legal": 1,
    "ai": 1,
    "vector": 1,
    "database": 1
  },
  "deferredTotal": 0,
  "deferredActive": 0,
  "portSearches": {
    "successes": 4,
    "failures": 0
  },
  "lastAllocation": {
    "type": "database",
    "port": 3040,
    "time": 1755617030466
  },
  "events": [
    {
      "e": "spawn:legal@3010",
      "t": 1755617030435
    },
    {
      "e": "spawn:ai@3020",
      "t": 1755617030446
    },
    {
      "e": "spawn:vector@3030",
      "t": 1755617030456
    },
    {
      "e": "spawn:database@3040",
      "t": 1755617030466
    }
  ],
  "workers": [
    {
      "type": "legal",
      "pid": 49280,
      "port": 3010,
      "status": "online",
      "uptimeSec": 1826
    },
    {
      "type": "ai",
      "pid": 43132,
      "port": 3020,
      "status": "online",
      "uptimeSec": 1826
    },
    {
      "type": "vector",
      "pid": 47168,
      "port": 3030,
      "status": "online",
      "uptimeSec": 1826
    },
    {
      "type": "database",
      "pid": 10928,
      "port": 3040,
      "status": "online",
      "uptimeSec": 1826
    }
  ],
  "deferredQueue": []
}